emcee_package/__init__.py
emcee_package/main.py
emcee_package-0.3.0.dist-info/METADATA
emcee_package-0.3.0.dist-info/WHEEL
emcee_package-0.3.0.dist-info/entry_points.txt
emcee_package-0.3.0.dist-info/RECORD
